LICENSE
MANIFEST.in
README.md
setup.py
AstroKundli/GKundli.py
AstroKundli/__init__.py
AstroKundli.egg-info/PKG-INFO
AstroKundli.egg-info/SOURCES.txt
AstroKundli.egg-info/dependency_links.txt
AstroKundli.egg-info/requires.txt
AstroKundli.egg-info/top_level.txt
FlatlibAstroSidereal/__init__.py
FlatlibAstroSidereal/angle.py
FlatlibAstroSidereal/aspects.py
FlatlibAstroSidereal/chart.py
FlatlibAstroSidereal/const.py
FlatlibAstroSidereal/datetime.py
FlatlibAstroSidereal/geopos.py
FlatlibAstroSidereal/lists.py
FlatlibAstroSidereal/object.py
FlatlibAstroSidereal/props.py
FlatlibAstroSidereal/utils.py
FlatlibAstroSidereal/dignities/__init__.py
FlatlibAstroSidereal/dignities/accidental.py
FlatlibAstroSidereal/dignities/essential.py
FlatlibAstroSidereal/dignities/tables.py
FlatlibAstroSidereal/ephem/__init__.py
FlatlibAstroSidereal/ephem/eph.py
FlatlibAstroSidereal/ephem/ephem.py
FlatlibAstroSidereal/ephem/swe.py
FlatlibAstroSidereal/ephem/tools.py
FlatlibAstroSidereal/predictives/__init__.py
FlatlibAstroSidereal/predictives/primarydirections.py
FlatlibAstroSidereal/predictives/profections.py
FlatlibAstroSidereal/predictives/returns.py
FlatlibAstroSidereal/protocols/__init__.py
FlatlibAstroSidereal/protocols/almutem.py
FlatlibAstroSidereal/protocols/behavior.py
FlatlibAstroSidereal/protocols/temperament.py
FlatlibAstroSidereal/resources/README.md
FlatlibAstroSidereal/resources/swefiles/fixstars.cat
FlatlibAstroSidereal/resources/swefiles/seas_12.se1
FlatlibAstroSidereal/resources/swefiles/seas_18.se1
FlatlibAstroSidereal/resources/swefiles/seas_24.se1
FlatlibAstroSidereal/resources/swefiles/semo_12.se1
FlatlibAstroSidereal/resources/swefiles/semo_18.se1
FlatlibAstroSidereal/resources/swefiles/semo_24.se1
FlatlibAstroSidereal/resources/swefiles/sepl_12.se1
FlatlibAstroSidereal/resources/swefiles/sepl_18.se1
FlatlibAstroSidereal/resources/swefiles/sepl_24.se1
FlatlibAstroSidereal/tools/__init__.py
FlatlibAstroSidereal/tools/arabicparts.py
FlatlibAstroSidereal/tools/chartdynamics.py
FlatlibAstroSidereal/tools/planetarytime.py